auto_semver/__init__.py
auto_semver/__main__.py
auto_semver/auto_semver.py
auto_semver/cli.py
auto_semver/file_replacer.py
auto_semver/git.py
auto_semver/semver.py
auto_semver-0.8.0.dist-info/LICENSE
auto_semver-0.8.0.dist-info/METADATA
auto_semver-0.8.0.dist-info/WHEEL
auto_semver-0.8.0.dist-info/entry_points.txt
auto_semver-0.8.0.dist-info/top_level.txt
auto_semver-0.8.0.dist-info/RECORD
