Metadata-Version: 2.1
Name: auto-semver
Version: 0.8.0
Summary: Semver swiss-army knife
Home-page: http://github.com/juliangindi/auto-semver
Author: Julian Gindi
Author-email: julian@gindi.io
License: MIT
Platform: UNKNOWN
